{"1": {"artist": "Luis Fonsi, Daddy Yankee, Justin Bieber", "song": "Despacito - Remix", "song_id": "5CtI0qwDJkDQGwXD1H1cLb"}, "2": {"artist": "DJ Khaled, Justin Bieber, Quavo, Chance the Rapper, Lil Wayne", "song": "I'm the One", "song_id": "72Q0FQQo32KJloivv5xge2"}, "3": {"artist": "Jason Derulo, Nicki Minaj, Ty Dolla $ign", "song": "Swalla (feat. Nicki Minaj & Ty Dolla $ign)", "song_id": "6kex4EBAj0WHXDKZMEJaaF"}, "4": {"artist": "Ed Sheeran", "song": "Shape of You", "song_id": "7qiZfU4dY1lWllzX7mPBI3"}, "5": {"artist": "Shawn Mendes", "song": "There's Nothing Holdin' Me Back", "song_id": "79cuOz3SPQTuFrp8WgftAu"}, "6": {"artist": "Luis Fonsi, Daddy Yankee", "song": "Despacito (Featuring Daddy Yankee)", "song_id": "4aWmUDTfIPGksMNLV2rQP2"}, "7": {"artist": "Clean Bandit, Zara Larsson", "song": "Symphony (feat. Zara Larsson)", "song_id": "1x5sYLZiu9r5E43kMlt9f8"}, "8": {"artist": "Alice Merton", "song": "No Roots", "song_id": "4bPWDXpN6MlTZBedxega3X"}, "9": {"artist": "Ed Sheeran", "song": "Galway Girl", "song_id": "0afhq8XCExXpqazXczTSve"}, "10": {"artist": "Burak Yeter, Danelle Sandoval", "song": "Tuesday", "song_id": "5c4tB0saSkNHX5CyDosuF7"}, "11": {"artist": "RAF Camora, Maxwell, Gzuz, Bonez MC", "song": "Kontrollieren", "song_id": "3H25ywsvlV0ZT2XSpSU7wk"}, "12": {"artist": "Future", "song": "Mask Off", "song_id": "3rOSwuTsUlJp0Pu0MkN8r8"}, "13": {"artist": "The Chainsmokers, Coldplay", "song": "Something Just Like This", "song_id": "6RUKPb4LETWmmr3iAEQktW"}, "14": {"artist": "Kygo, Selena Gomez", "song": "It Ain't Me (with Selena Gomez)", "song_id": "3eR23VReFzcdmS7TYCrhCe"}, "15": {"artist": "KC Rebell, Summer Cem", "song": "Murcielago", "song_id": "0p6ZRPPmXONaxaqWVdBZmD"}, "16": {"artist": "Maggie Lindemann, CADE, Cheat Codes", "song": "Pretty Girl - Cheat Codes X CADE Remix", "song_id": "39IsH7B5byx8NRlEKlZVg9"}, "17": {"artist": "Imagine Dragons", "song": "Thunder", "song_id": "56lBX2WHqfGuoeZxZvUnVj"}, "18": {"artist": "Jax Jones, RAYE", "song": "You Don't Know Me - Radio Edit", "song_id": "4WrS6vezaPwOafKJmHqMEU"}, "19": {"artist": "Zedd, Alessia Cara", "song": "Stay (with Alessia Cara)", "song_id": "0dA2Mk56wEzDgegdC6R17g"}, "20": {"artist": "G-Eazy, Kehlani", "song": "Good Life (with G-Eazy & Kehlani)", "song_id": "1Eck97uRMlprKOOJN9oO1E"}, "21": {"artist": "French Montana, Swae Lee", "song": "Unforgettable", "song_id": "1F2HXIJrE2Xn81OzT2zZvW"}, "22": {"artist": "Zuna, Azet, Noizy", "song": "Nummer 1", "song_id": "3sgGmPQD2J6aQduN36RDBO"}, "23": {"artist": "Kygo, Ellie Goulding", "song": "First Time", "song_id": "2Gl0FzuLxflY6nPifJp5Dr"}, "24": {"artist": "Kendrick Lamar", "song": "HUMBLE.", "song_id": "7KXjTSCq5nL1LoYtL7XAwS"}, "25": {"artist": "Miley Cyrus", "song": "Malibu", "song_id": "2habSXqcJGExM6JJyskY7O"}, "26": {"artist": "Alle Farben, Janieck", "song": "Little Hollywood", "song_id": "1f3flfdU4VDM2OBDD2FMia"}, "27": {"artist": "Enrique Iglesias, Descemer Bueno, Zion & Lennox", "song": "SUBEME LA RADIO (feat. Descemer Bueno & Zion & Lennox)", "song_id": "7nKBxz47S9SD79N086fuhn"}, "28": {"artist": "Charlie Puth", "song": "Attention", "song_id": "4iLqG9SeJSnt0cSPICSjxv"}, "29": {"artist": "Anne-Marie", "song": "Ciao Adios", "song_id": "3EfugazgSddQvzZpkof5I4"}, "30": {"artist": "Imagine Dragons", "song": "Believer", "song_id": "6VRghJeP6I0w1KxkdWFfIh"}, "31": {"artist": "Kurdo", "song": "Ya Salam", "song_id": "5fpujciVjGBhnR2XFx06E7"}, "32": {"artist": "Martin Garrix, Dua Lipa", "song": "Scared to Be Lonely", "song_id": "3ebXMykcMXOcLeJ9xZ17XH"}, "33": {"artist": "ALMA", "song": "Chasing Highs", "song_id": "6fTsxhIosAU6zXTAhSaemI"}, "34": {"artist": "Martin Jensen", "song": "Solo Dance", "song_id": "6HUnnBwYZqcED1eQztxMBN"}, "35": {"artist": "Welshly Arms", "song": "Legendary", "song_id": "1HxvdVlvQH5NUPi1wsq5L1"}, "36": {"artist": "RIN", "song": "Bros", "song_id": "2PcREcTtGiNTUCM4g2Qg4Z"}, "37": {"artist": "KC Rebell, Summer Cem", "song": "Nicht jetzt", "song_id": "6hB5hpMGCIriSNCH0d2zHY"}, "38": {"artist": "Nimo", "song": "LFR", "song_id": "2gFYrhAsBGU9DUzOiCy16l"}, "39": {"artist": "Bonez MC, RAF Camora, Maxwell", "song": "Ohne mein Team", "song_id": "05Mp2UJulSttxQ4E6hQPH3"}, "40": {"artist": "Julia Michaels", "song": "Issues", "song_id": "1sXUWdKx03aP9Gmzft58rt"}, "41": {"artist": "Harry Styles", "song": "Sign of the Times", "song_id": "5Ohxk2dO5COHF1krpoPigN"}, "42": {"artist": "The Chainsmokers", "song": "Paris", "song_id": "72jbDTw1piOOj770jWNeaG"}, "43": {"artist": "AJR", "song": "Weak", "song_id": "6OuV4vfyb8v3vGGGksqyKf"}, "44": {"artist": "Adel Tawil", "song": "Ist da jemand", "song_id": "1QzmdyU1N47jAj0ao5IvlW"}, "45": {"artist": "Starley, Ryan Riback", "song": "Call On Me - Ryan Riback Extended Remix", "song_id": "78rIJddV4X0HkNAInEcYde"}, "46": {"artist": "JP Cooper", "song": "September Song", "song_id": "0FuTx2s3YH1ppmtiM6l0zI"}, "47": {"artist": "Drake", "song": "Passionfruit", "song_id": "7hDc8b7IXETo14hHIHdnhd"}, "48": {"artist": "Fake Pictures", "song": "Two Princes - Radio Mix", "song_id": "1iTKkkgXj8kJkGdjGGBFqL"}, "49": {"artist": "GIMS, Dany Synth\u00e9, SoFLY & Nius", "song": "Loin (feat. Dany Synth\u00e9 & soFLY & Nius) - Pilule violette", "song_id": "3up1uPuvL5vkfJ6aOeSRtD"}, "50": {"artist": "Cheat Codes, Demi Lovato", "song": "No Promises (feat. Demi Lovato)", "song_id": "1louJpMmzEicAn7lzDalPW"}}